telewater/__init__.py
telewater/bot.py
telewater/cli.py
telewater/conf.py
telewater/main.py
telewater/utils.py
telewater-0.1.5.post2.dist-info/entry_points.txt
telewater-0.1.5.post2.dist-info/LICENSE
telewater-0.1.5.post2.dist-info/WHEEL
telewater-0.1.5.post2.dist-info/METADATA
telewater-0.1.5.post2.dist-info/RECORD
