Metadata-Version: 2.1
Name: telewater
Version: 0.1.5.post2
Summary: A telegram bot that applies watermark on images, gifs and videos.
Home-page: https://github.com/aahnik/telewater
License: MIT
Keywords: telegram,watermark,bot,async
Author: aahnik
Author-email: daw@aahnik.dev
Requires-Python: >=3.9,<4.0
Classifier: License :: OSI Approved :: MIT License
Classifier: Operating System :: OS Independent
Classifier: Programming Language :: Cython
Classifier: Programming Language :: Python :: 3
Classifier: Programming Language :: Python :: 3.9
Classifier: Topic :: Software Development
Requires-Dist: Pillow (>=8.1.2,<9.0.0)
Requires-Dist: PyYAML (>=5.4.1,<6.0.0)
Requires-Dist: Telethon (>=1.21.1,<2.0.0)
Requires-Dist: aiohttp (>=3.7.4,<4.0.0)
Requires-Dist: cryptg (>=0.2.post2,<0.3)
Requires-Dist: hachoir (>=3.1.2,<4.0.0)
Requires-Dist: pydantic (>=1.8.1,<2.0.0)
Requires-Dist: python-dotenv (>=0.16.0,<0.17.0)
Requires-Dist: requests (>=2.25.1,<3.0.0)
Requires-Dist: typer (>=0.3.2,<0.4.0)
Requires-Dist: watermark.py (>=0.0.3.post3,<0.0.4)
Project-URL: Repository, https://github.com/aahnik/telewater
